<?xml version="1.0" encoding="UTF-8"?><database>
    <element db_object_id="50b43c9893500310414ef2375d03d6d5" label="Machines" max_length="40" name="x_1964226_svem_com_machines" type="collection">
        <element attributes="encode_utf8=false" label="Current Job" max_length="32" name="current_job" reference="x_1964226_svem_com_jobs" type="reference"/>
        <element attributes="edge_encryption_enabled=true" display="true" label="Machine Name" mandatory="true" max_length="100" name="machine_name" type="string"/>
        <element label="Machine Number" mandatory="true" max_length="40" name="machine_number" type="integer"/>
        <element function_definition="glidefunction:count_queued_jobs" function_field="true" label="Jobs Queued" max_length="40" name="total_jobs_queued" read_only="true" type="integer"/>
        <element choice="1" label="Machine Type" max_length="40" name="machine_type" type="choice">
            <choice>
                <element inactive_on_update="false" label="Lathe" sequence="1" value="lathe"/>
                <element inactive_on_update="false" label="Vertical Mill" sequence="0" value="vertical_mill"/>
            </choice>
        </element>
        <element attributes="edge_encryption_enabled=true" label="Notes" max_length="4000" name="notes" type="string"/>
        <element attributes="edge_encryption_enabled=true" function_definition="glidefunction:calculate_next_available" function_field="true" label="Next Available" max_length="40" name="next_available" read_only="true" type="glide_date_time"/>
        <element function_definition="glidefunction:calculate_uptime_percentage" function_field="true" label="Uptime %" max_length="20" name="uptime_percentage" read_only="true" type="decimal"/>
        <element choice="1" default="idle" label="Status" max_length="40" name="status" type="choice">
            <choice>
                <element inactive_on_update="false" label="Maintenance" sequence="2" value="maintenance"/>
                <element inactive_on_update="false" label="Idle" sequence="1" value="idle"/>
                <element inactive_on_update="false" label="Running" sequence="0" value="running"/>
                <element inactive_on_update="false" label="Offline" sequence="3" value="offline"/>
            </choice>
        </element>
        <index name="index">
            <element name="current_job"/>
        </index>
    </element>
</database>
